azure/mgmt/databasewatcher/__init__.py
azure/mgmt/databasewatcher/_client.py
azure/mgmt/databasewatcher/_configuration.py
azure/mgmt/databasewatcher/_model_base.py
azure/mgmt/databasewatcher/_patch.py
azure/mgmt/databasewatcher/_serialization.py
azure/mgmt/databasewatcher/_validation.py
azure/mgmt/databasewatcher/_version.py
azure/mgmt/databasewatcher/py.typed
azure/mgmt/databasewatcher/aio/__init__.py
azure/mgmt/databasewatcher/aio/_client.py
azure/mgmt/databasewatcher/aio/_configuration.py
azure/mgmt/databasewatcher/aio/_patch.py
azure/mgmt/databasewatcher/aio/operations/__init__.py
azure/mgmt/databasewatcher/aio/operations/_operations.py
azure/mgmt/databasewatcher/aio/operations/_patch.py
azure/mgmt/databasewatcher/models/__init__.py
azure/mgmt/databasewatcher/models/_enums.py
azure/mgmt/databasewatcher/models/_models.py
azure/mgmt/databasewatcher/models/_patch.py
azure/mgmt/databasewatcher/operations/__init__.py
azure/mgmt/databasewatcher/operations/_operations.py
azure/mgmt/databasewatcher/operations/_patch.py
azure_mgmt_databasewatcher-1.0.0b1.dist-info/LICENSE
azure_mgmt_databasewatcher-1.0.0b1.dist-info/METADATA
azure_mgmt_databasewatcher-1.0.0b1.dist-info/WHEEL
azure_mgmt_databasewatcher-1.0.0b1.dist-info/top_level.txt
azure_mgmt_databasewatcher-1.0.0b1.dist-info/RECORD
